{
  "id": "ccb-pre-post-loan-query-doubao",
  "displayName": "CCB贷前贷后查询",
  "mode": "browser-task",
  "targetEnvironments": ["pc-local-browser", "web-remote-browser", "mobile-supervised-task"],
  "startupNotice": [
    "我会打开所有需要你注意的页面。",
    "请登录中国裁判文书网。",
    "中国执行信息公开网可能需要登录，并且经常加载失败，重试是正常情况。",
    "请在每个执行公开网页面只输入验证码。",
    "验证码错误或页面没有进入查询结果/无结果时，我不会截图，会继续等你重新输入。"
  ],
  "stateMachine": [
    "collect_subject",
    "open_manual_pages",
    "wait_login_or_user_takeover",
    "fill_non_captcha_fields",
    "wait_captcha_input",
    "submit_query",
    "validate_result_state",
    "retry_on_captcha_or_load_failure",
    "capture_confirmed_pages",
    "build_report"
  ],
  "validationRules": {
    "enforcementMustReachResultState": true,
    "rejectLoginCaptchaErrorBlankPages": true,
    "dynamicScreenshots": true,
    "captchaBypass": false
  },
  "optionalOcr": {
    "provider": "ddddocr",
    "defaultEnabled": false,
    "policy": "Only for compliant OCR tasks. Do not use to bypass judicial/enforcement captcha or access controls."
  }
}
